QianruQianchuAndroidAnquan/README.md
QianruQianchuAndroidAnquan/__init__.py
QianruQianchuAndroidAnquan/__main__.py
QianruQianchuAndroidAnquan/file.epub
QianruQianchuAndroidAnquan/index.html
QianruQianchuAndroidAnquan/css/__init__.py
QianruQianchuAndroidAnquan/css/annotations.css
QianruQianchuAndroidAnquan/css/main.css
QianruQianchuAndroidAnquan/css/normalize.css
QianruQianchuAndroidAnquan/css/popup.css
QianruQianchuAndroidAnquan/font/__init__.py
QianruQianchuAndroidAnquan/font/fontello.eot
QianruQianchuAndroidAnquan/font/fontello.svg
QianruQianchuAndroidAnquan/font/fontello.ttf
QianruQianchuAndroidAnquan/font/fontello.woff
QianruQianchuAndroidAnquan/img/__init__.py
QianruQianchuAndroidAnquan/img/annotator-glyph-sprite.png
QianruQianchuAndroidAnquan/img/annotator-icon-sprite.png
QianruQianchuAndroidAnquan/img/apple-touch-icon.png
QianruQianchuAndroidAnquan/img/cancelfullscreen.png
QianruQianchuAndroidAnquan/img/close.png
QianruQianchuAndroidAnquan/img/fullscreen.png
QianruQianchuAndroidAnquan/img/loader.gif
QianruQianchuAndroidAnquan/img/menu-icon.png
QianruQianchuAndroidAnquan/img/save.png
QianruQianchuAndroidAnquan/img/saved.png
QianruQianchuAndroidAnquan/img/settings-s.png
QianruQianchuAndroidAnquan/img/settings.png
QianruQianchuAndroidAnquan/img/star.png
QianruQianchuAndroidAnquan/js/__init__.py
QianruQianchuAndroidAnquan/js/epub.js
QianruQianchuAndroidAnquan/js/epub.min.js
QianruQianchuAndroidAnquan/js/epub.min.map
QianruQianchuAndroidAnquan/js/hooks.min.js
QianruQianchuAndroidAnquan/js/hooks.min.map
QianruQianchuAndroidAnquan/js/reader.js
QianruQianchuAndroidAnquan/js/reader.js.map
QianruQianchuAndroidAnquan/js/reader.min.js
QianruQianchuAndroidAnquan/js/reader.min.map
QianruQianchuAndroidAnquan/js/hooks/__init__.py
QianruQianchuAndroidAnquan/js/hooks/extensions/__init__.py
QianruQianchuAndroidAnquan/js/hooks/extensions/highlight.js
QianruQianchuAndroidAnquan/js/libs/__init__.py
QianruQianchuAndroidAnquan/js/libs/jquery.min.js
qianru_qianchu_android_anquan-2024.3.1.0.dist-info/METADATA
qianru_qianchu_android_anquan-2024.3.1.0.dist-info/WHEEL
qianru_qianchu_android_anquan-2024.3.1.0.dist-info/entry_points.txt
qianru_qianchu_android_anquan-2024.3.1.0.dist-info/top_level.txt
qianru_qianchu_android_anquan-2024.3.1.0.dist-info/RECORD
